miriel/__init__.py
miriel/miriel.py
miriel_python-0.2.5.dist-info/licenses/LICENSE
tests/data/IMG_7146.jpg
tests/data/test.log
tests/data/testbirb.png
miriel_python-0.2.5.dist-info/METADATA
miriel_python-0.2.5.dist-info/WHEEL
miriel_python-0.2.5.dist-info/top_level.txt
miriel_python-0.2.5.dist-info/RECORD
