Metadata-Version: 2.4
Name: miriel-python
Version: 0.2.5
Summary: Library for interacting with the Miriel API
Author-email: Andy Barkett <andy@miriel.ai>
License: MIT
Project-URL: Homepage, https://github.com/miriel-ai/miriel-python
Classifier: Programming Language :: Python :: 3
Classifier: License :: OSI Approved :: MIT License
Classifier: Operating System :: OS Independent
Requires-Python: >=3.8
License-File: LICENSE
Requires-Dist: requests>=2.0
Requires-Dist: python-json-logger>=2.0.7
Provides-Extra: dev
Requires-Dist: build>=1.0; extra == "dev"
Requires-Dist: pytest>=7.0; extra == "dev"
Requires-Dist: ruff; extra == "dev"
Dynamic: license-file
